{
    "cloneOrigin": "5673de654bdc2d180f8b456d",
    "id": "6a43f00138a6d33bffe98310",
    "fleaPrice": 1.1,
    "handBookPrice": 1.1,
    "includeInSameQuestsAsOrigin": true,
    "addSpawnsInSamePlacesAsOrigin": true,
    "spawnWeightComparedToOrigin": 0.1,
    "effects_health": {
        "Hydration": {
            "value": -4
        },
        "Energy": {
            "value": 52
        }
    },
    "Buffs": [
        {
            "AbsoluteValue": true,
            "BuffType": "EnergyRate",
            "Chance": 1,
            "Delay": 0,
            "Duration": 60,
            "SkillName": "",
            "Value": 0.15
        },
        {
            "AbsoluteValue": true,
            "BuffType": "SkillRate",
            "Chance": 1,
            "Delay": 0,
            "Duration": 90,
            "SkillName": "Strength",
            "Value": 1
        }
    ],
    "locales": {
        "en": {
            "name": "Can of Cooked Pacific saury",
            "shortName": "Cooked Saury",
            "description": "Pacific saury, warmed until the oil starts moving and the label stops mattering. Built for long raids where pride already died. Salty, fishy, and warm enough to make a backroom crate feel like dinner."
        }
    },
    "trader": {
        "traderId": "66a0f6b2c4d8e90123456789",
        "loyaltyReq": 2,
        "price": 57500,
        "amountForSale": 30,
        "buyRestrictionMax": 2,
        "assortmentId": "6a447e1638a6d33bffe98304"
    },
    "craft": {
        "_id": "6a43f01138a6d33bffe98320",
        "areaType": 5,
        "requirements": [
            {
                "areaType": 5,
                "requiredLevel": 1,
                "type": "Area"
            },
            {
                "templateId": "57347b8b24597737dd42e192",
                "type": "Tool"
            },
            {
                "templateId": "5d1b36a186f7742523398433",
                "type": "Tool"
            },
            {
                "templateId": "5673de654bdc2d180f8b456d",
                "count": 1,
                "isFunctional": false,
                "isEncoded": false,
                "type": "Item"
            }
        ],
        "productionTime": 2700,
        "needFuelForAllProductionTime": false,
        "locked": false,
        "endProduct": "6a43f00138a6d33bffe98310",
        "continuous": false,
        "count": 1,
        "productionLimitCount": 0,
        "isEncoded": false
    }
}
